rpyg/__init__.py
rpyg/initial.py
test/__init__.py
test/test_initial.py
rpyg-0.3.dist-info/LICENSE
rpyg-0.3.dist-info/METADATA
rpyg-0.3.dist-info/WHEEL
rpyg-0.3.dist-info/top_level.txt
rpyg-0.3.dist-info/RECORD
